LICENSE
README.md
tap_mongodb/__init__.py
tap_mongodb/collection.py
tap_mongodb/tap.py
tap_mongodb/tests/__init__.py
tap_mongodb/tests/test_core.py
z3_tap_mongodb-0.4.5.dist-info/LICENSE
z3_tap_mongodb-0.4.5.dist-info/WHEEL
z3_tap_mongodb-0.4.5.dist-info/entry_points.txt
z3_tap_mongodb-0.4.5.dist-info/METADATA
z3_tap_mongodb-0.4.5.dist-info/RECORD
