Metadata-Version: 2.1
Name: z3-tap-mongodb
Version: 0.4.5
Summary: z3-tap-mongodb is a Singer tap for MongoDB, built with the Meltano SDK for Singer Taps.
Home-page: https://github.com/z3z1ma/tap-mongodb
License: Apache 2.0
Keywords: ELT,MongoDB
Author: Alex Butler
Author-email: butler.alex2010@gmail.com
Requires-Python: >=3.7.1,<3.12
Classifier: Development Status :: 4 - Beta
Classifier: Environment :: Console
Classifier: Intended Audience :: Developers
Classifier: License :: OSI Approved :: MIT License
Classifier: License :: Other/Proprietary License
Classifier: Operating System :: OS Independent
Classifier: Programming Language :: Python :: 3
Classifier: Programming Language :: Python :: 3.8
Classifier: Programming Language :: Python :: 3.9
Classifier: Programming Language :: Python :: 3.10
Classifier: Programming Language :: Python :: 3.11
Classifier: Programming Language :: Python :: 3.10
Classifier: Programming Language :: Python :: 3.8
Classifier: Programming Language :: Python :: 3.9
Classifier: Topic :: Software Development :: Libraries :: Python Modules
Classifier: Typing :: Typed
Requires-Dist: genson (>=1.2.2,<2.0.0)
Requires-Dist: orjson (>=3.8.2)
Requires-Dist: pymongo[srv] (>=4.3.3)
Requires-Dist: requests (>=2.25.1)
Requires-Dist: singer-sdk (>=0.17.0)
Project-URL: Repository, https://github.com/z3z1ma/tap-mongodb
